jupyterlab_cell_input_footer/__init__.py
jupyterlab_cell_input_footer/_version.py
jupyterlab_cell_input_footer-0.3.2.data/data/share/jupyter/labextensions/jupyterlab-cell-input-footer-extension/package.json
jupyterlab_cell_input_footer-0.3.2.data/data/share/jupyter/labextensions/jupyterlab-cell-input-footer-extension/schemas/jupyterlab-cell-input-footer-extension/package.json.orig
jupyterlab_cell_input_footer-0.3.2.data/data/share/jupyter/labextensions/jupyterlab-cell-input-footer-extension/static/374.f7ab05aeba5c1aa173c9.js
jupyterlab_cell_input_footer-0.3.2.data/data/share/jupyter/labextensions/jupyterlab-cell-input-footer-extension/static/432.7cb3263d05824765a0d2.js
jupyterlab_cell_input_footer-0.3.2.data/data/share/jupyter/labextensions/jupyterlab-cell-input-footer-extension/static/509.9384daafd8fb72a4ff3a.js
jupyterlab_cell_input_footer-0.3.2.data/data/share/jupyter/labextensions/jupyterlab-cell-input-footer-extension/static/993.f7ab05aeba5c1aa173c9.js
jupyterlab_cell_input_footer-0.3.2.data/data/share/jupyter/labextensions/jupyterlab-cell-input-footer-extension/static/remoteEntry.f80ac7a8e97b08d2a2fd.js
jupyterlab_cell_input_footer-0.3.2.data/data/share/jupyter/labextensions/jupyterlab-cell-input-footer-extension/static/style.js
jupyterlab_cell_input_footer-0.3.2.data/data/share/jupyter/labextensions/jupyterlab-cell-input-footer-extension/static/third-party-licenses.json
jupyterlab_cell_input_footer-0.3.2.data/data/share/jupyter/labextensions/jupyterlab-cell-input-footer-extension/install.json
jupyterlab_cell_input_footer-0.3.2.dist-info/METADATA
jupyterlab_cell_input_footer-0.3.2.dist-info/WHEEL
jupyterlab_cell_input_footer-0.3.2.dist-info/licenses/LICENSE
jupyterlab_cell_input_footer-0.3.2.dist-info/RECORD
