Metadata-Version: 2.4
Name: jupyterlab_cell_input_footer
Version: 0.3.2
Summary: A JupyterLab Plugin that adds a footer to cell inputs.
Project-URL: Homepage, https://github.com/jupyter-ai-contrib/jupyterlab-cell-input-footer
Project-URL: Bug Tracker, https://github.com/jupyter-ai-contrib/jupyterlab-cell-input-footer/issues
Project-URL: Repository, https://github.com/jupyter-ai-contrib/jupyterlab-cell-input-footer.git
Author-email: Zach Sailer <zachsailer@gmail.com>
License: BSD 3-Clause License
License-File: LICENSE
Keywords: jupyter,jupyterlab,jupyterlab-extension
Classifier: Framework :: Jupyter
Classifier: Framework :: Jupyter :: JupyterLab
Classifier: Framework :: Jupyter :: JupyterLab :: 4
Classifier: Framework :: Jupyter :: JupyterLab :: Extensions
Classifier: Framework :: Jupyter :: JupyterLab :: Extensions :: Prebuilt
Classifier: License :: OSI Approved :: BSD License
Classifier: Programming Language :: Python
Classifier: Programming Language :: Python :: 3
Classifier: Programming Language :: Python :: 3.8
Classifier: Programming Language :: Python :: 3.9
Classifier: Programming Language :: Python :: 3.10
Classifier: Programming Language :: Python :: 3.11
Classifier: Programming Language :: Python :: 3.12
Requires-Python: >=3.8
Requires-Dist: jupyterlab<5,>=4
